insta_collect/__init__.py
insta_collect/cli.py
insta_collect/exporter.py
insta_collect/html_parser.py
insta_collect/insta-collect.py
insta_collect/main.py
insta_collect/saver.py
insta_collect/scraper.py
insta_collect-0.1.1.dist-info/METADATA
insta_collect-0.1.1.dist-info/WHEEL
insta_collect-0.1.1.dist-info/entry_points.txt
insta_collect-0.1.1.dist-info/top_level.txt
insta_collect-0.1.1.dist-info/RECORD
