Metadata-Version: 2.4
Name: insta-collect
Version: 0.1.1
Summary:  Modular Instagram Data Collector
Author-email: Alam Mahadika <alam.mahadika.psm@umy.ac.id>
License: MIT
Project-URL: Homepage, https://github.com/Alammahadika/insta-collect
Keywords: instagram,scraper,hashtag,comments,Posting
Requires-Python: >=3.10
Requires-Dist: beautifulsoup4>=4.12.2
Requires-Dist: lxml>=4.9.3
Requires-Dist: pandas>=2.1.0
Requires-Dist: openpyxl>=3.1.2
Requires-Dist: requests>=2.31.0
Requires-Dist: tqdm>=4.65.0
